exitstatus/__init__.py
exitstatus/py.typed
exitstatus-2.7.0.dist-info/licenses/LICENSE.txt
exitstatus-2.7.0.dist-info/WHEEL
exitstatus-2.7.0.dist-info/METADATA
exitstatus-2.7.0.dist-info/RECORD
