Metadata-Version: 2.4
Name: exitstatus
Version: 2.7.0
Summary: POSIX exit status codes
Keywords: exit,status,POSIX
Author: John Hagen
Author-email: John Hagen <johnthagen@gmail.com>
License-Expression: MIT
License-File: LICENSE.txt
Classifier: Development Status :: 5 - Production/Stable
Classifier: License :: OSI Approved :: MIT License
Classifier: Operating System :: OS Independent
Classifier: Programming Language :: Python
Classifier: Programming Language :: Python :: 3
Classifier: Programming Language :: Python :: 3.10
Classifier: Programming Language :: Python :: 3.11
Classifier: Programming Language :: Python :: 3.12
Classifier: Programming Language :: Python :: 3.13
Classifier: Programming Language :: Python :: 3.14
Classifier: Typing :: Typed
Requires-Python: >=3.10
Project-URL: Homepage, https://github.com/johnthagen/exitstatus
Project-URL: Repository, https://github.com/johnthagen/exitstatus
